{
  "css/carousel.css": "css/carousel-a312769d2a.css",
  "css/chat_box.css": "css/chat_box-0e63343637.css",
  "css/chat_box_master_room.css": "css/chat_box_master_room-c1b67a8293.css",
  "css/footer.css": "css/footer-efb0b3bb51.css",
  "css/header.css": "css/header-bae9b6870e.css",
  "css/home.css": "css/home-cb61093d3f.css",
  "css/layout.css": "css/layout-373c4167bf.css",
  "css/post.css": "css/post-f3d91dcf32.css",
  "css/user_profile.css": "css/user_profile-8c9f7883c5.css",
  "css/user_sign_in.css": "css/user_sign_in-a387fe486f.css",
  "css/user_sign_up.css": "css/user_sign_up-464961c547.css"
}